verushash/__init__.py
verushash/verushash.py
verushash-0.1.0.dist-info/LICENSE
verushash-0.1.0.dist-info/METADATA
verushash-0.1.0.dist-info/WHEEL
verushash-0.1.0.dist-info/top_level.txt
verushash-0.1.0.dist-info/RECORD
