Metadata-Version: 2.1
Name: verushash
Version: 0.1.0
Summary: Hash wrapper
Home-page: https://github.com/minnicknathan47/verushash
Author: Nathan Minnick
Author-email: minnicknathan47@gmail.com)
Classifier: Programming Language :: Python :: 3
Classifier: License :: OSI Approved :: MIT License
Classifier: Operating System :: OS Independent
Requires-Python: >=3.6
License-File: LICENSE
